{
	"keyboard":{
		"repeat":{
			"rate":25,
			"delay":600
		},
		"xkb":{
			"options":""
		},
		"chords":[
			{
				"pattern":"Sh-S-Q",
				"action":[
					"terminate"
				]
			},
			{
				"pattern":"S-q",
				"action":[
					"close"
				]
			},
			{
				"pattern":"S-Return",
				"action":[
					"spawn",
					"foot"
				]
			},
			{
				"pattern":"S-x S-f",
				"action":[
					"spawn",
					"nautilus"
				]
			},
			{
				"pattern":"S-m",
				"action":[
					"control"
				]
			},
			{
				"pattern":"S-i",
				"action":[
					"inc_master"
				]
			},
			{
				"pattern":"S-d",
				"action":[
					"dec_master"
				]
			},
			{
				"pattern":"S-h",
				"action":[
					"dec_mfact"
				]
			},
			{
				"pattern":"S-l",
				"action":[
					"inc_mfact"
				]
			}
		]
	},
	"panel":{
		"enabled":true,
		"font":"monospace bold 15",
		"colors":{
			"foreground":"#e5f2ffff",
			"background":"#000000ff",
			"accent":"#353535ff",
			"gray1":"#464646ff",
			"gray2":"#9a9a9aff",
			"border":"#999999ff",
			"seperator":"#7f7f7fff",
			"chord":"#cc9933ff"
		}
	},
	"views":{
		"border":{
			"thickness":2,
			"colors":{
				"active":"#334ccc7f",
				"inactive":"#7f7f7fff"
			}
		}
	},
	"monitors":{
		"default_scale":1.0,
		"wallpaper":{
			"filepath":"",
			"mode":"fit"
		}
	},
	"tiling":{
		"mode":"traditional",
		"gaps":10
	}
}
